Workbook

Sheet Produtos
A1: id | B1: nome | C1: categoria | D1: subcategoria | E1: marca | F1: embalagem | G1: unidadeVenda | H1: preco | I1: caixaQuantidade | J1: caixaPreco | K1: foto | L1: disponivel | M1: destaque | N1: descricao | O1: publicar | P1: codigoSistema | Q1: ean | R1: status | S1: observacao | T1: estoqueSistema | U1: precoRevenda
A2: polpa-de-acerola-brasfrut-pacote-com-12-100-g | B2: Polpa de Acerola | C2: polpas | D2: Polpa 100 g | E2: Brasfrut | F2: Pacote com 12 × 100 g | G2: pacote | H2: 30 | L2: =TRUE() -> TRUE | M2: =FALSE() -> FALSE | O2: =TRUE() -> TRUE | P2: 50003 | Q2: 7896014400287 | R2: Ok | T2: 154 | U2: 38
A3: polpa-de-cacau-brasfrut-pacote-com-12-100-g | B3: Polpa de Cacau | C3: polpas | D3: Polpa 100 g | E3: Brasfrut | F3: Pacote com 12 × 100 g | G3: pacote | H3: 30 | L3: =TRUE() -> TRUE | M3: =FALSE() -> FALSE | O3: =TRUE() -> TRUE | P3: 50004 | Q3: 7896014400379 | R3: Ok | T3: 19 | U3: 38
A4: polpa-de-caja-brasfrut-pacote-com-12-100-g | B4: Polpa de Cajá | C4: polpas | D4: Polpa 100 g | E4: Brasfrut | F4: Pacote com 12 × 100 g | G4: pacote | H4: 40 | L4: =TRUE() -> TRUE | M4: =FALSE() -> FALSE | O4: =TRUE() -> TRUE | P4: 50005 | Q4: 7896014400461 | R4: Ok | T4: 128 | U4: 50
A5: polpa-de-caju-brasfrut-pacote-com-12-100-g | B5: Polpa de Caju | C5: polpas | D5: Polpa 100 g | E5: Brasfrut | F5: Pacote com 12 × 100 g | G5: pacote | H5: 30 | L5: =TRUE() -> TRUE | M5: =FALSE() -> FALSE | O5: =TRUE() -> TRUE | P5: 50006 | Q5: 7896014400553 | R5: Ok | T5: 87 | U5: 38
A6: polpa-de-cupuacu-brasfrut-pacote-com-12-100-g | B6: Polpa de Cupuaçu | C6: polpas | D6: Polpa 100 g | E6: Brasfrut | F6: Pacote com 12 × 100 g | G6: pacote | H6: 35 | L6: =TRUE() -> TRUE | M6: =FALSE() -> FALSE | O6: =TRUE() -> TRUE | P6: 50007 | Q6: 7896014499007 | R6: Ok | T6: 47
A7: polpa-de-goiaba-brasfrut-pacote-com-12-100-g | B7: Polpa de Goiaba | C7: polpas | D7: Polpa 100 g | E7: Brasfrut | F7: Pacote com 12 × 100 g | G7: pacote | H7: 30 | L7: =TRUE() -> TRUE | M7: =FALSE() -> FALSE | O7: =TRUE() -> TRUE | P7: 50008 | Q7: 7896014400645 | R7: Ok | T7: 22 | U7: 38
A8: polpa-de-graviola-brasfrut-pacote-com-12-100-g | B8: Polpa de Graviola | C8: polpas | D8: Polpa 100 g | E8: Brasfrut | F8: Pacote com 12 × 100 g | G8: pacote | H8: 40 | L8: =TRUE() -> TRUE | M8: =FALSE() -> FALSE | O8: =TRUE() -> TRUE | P8: 50009 | Q8: 7896014401079 | R8: Ok | T8: 21 | U8: 50
A9: polpa-de-manga-brasfrut-pacote-com-12-100-g | B9: Polpa de Manga | C9: polpas | D9: Polpa 100 g | E9: Brasfrut | F9: Pacote com 12 × 100 g | G9: pacote | H9: 30 | L9: =TRUE() -> TRUE | M9: =FALSE() -> FALSE | O9: =TRUE() -> TRUE | P9: 50011 | Q9: 7896014400737 | R9: Ok | T9: 36 | U9: 38
A10: polpa-de-maracuja-brasfrut-pacote-com-12-100-g | B10: Polpa de Maracujá | C10: polpas | D10: Polpa 100 g | E10: Brasfrut | F10: Pacote com 12 × 100 g | G10: pacote | H10: 60 | L10: =TRUE() -> TRUE | M10: =FALSE() -> FALSE | O10: =TRUE() -> TRUE | P10: 50013 | Q10: 7896014400829 | R10: Ok | T10: 320 | U10: 70
A11: polpa-de-morango-brasfrut-pacote-com-12-100-g | B11: Polpa de Morango | C11: polpas | D11: Polpa 100 g | E11: Brasfrut | F11: Pacote com 12 × 100 g | G11: pacote | H11: 40 | L11: =TRUE() -> TRUE | M11: =FALSE() -> FALSE | O11: =TRUE() -> TRUE | P11: 50015 | Q11: 7896014403103 | R11: Ok | T11: 245 | U11: 50
A12: polpa-de-uva-brasfrut-pacote-com-12-100-g | B12: Polpa de Uva | C12: polpas | D12: Polpa 100 g | E12: Brasfrut | F12: Pacote com 12 × 100 g | G12: pacote | H12: 60 | L12: =TRUE() -> TRUE | M12: =FALSE() -> FALSE | O12: =TRUE() -> TRUE | P12: 50018 | Q12: 7896014403455 | R12: Ok | T12: 64
A13: polpa-de-tamarindo-brasfrut-pacote-com-12-100-g | B13: Polpa de Tamarindo | C13: polpas | D13: Polpa 100 g | E13: Brasfrut | F13: Pacote com 12 × 100 g | G13: pacote | H13: 30 | L13: =TRUE() -> TRUE | M13: =FALSE() -> FALSE | O13: =TRUE() -> TRUE | P13: 50019 | Q13: 7896014490004 | R13: Ok | T13: 142 | U13: 38
A14: polpa-de-abacaxi-brasfrut-pacote-com-12-100-g | B14: Polpa de Abacaxi | C14: polpas | D14: Polpa 100 g | E14: Brasfrut | F14: Pacote com 12 × 100 g | G14: pacote | H14: 30 | L14: =TRUE() -> TRUE | M14: =FALSE() -> FALSE | O14: =TRUE() -> TRUE | P14: 50001 | Q14: 7896014400195 | R14: Ok | T14: 184 | U14: 38
A15: polpa-de-abacaxi-nutricau-pacote-com-12-100-g | B15: Polpa de Abacaxi | C15: polpas | D15: Polpa 100 g | E15: Nutricau | F15: Pacote com 12 × 100 g | G15: pacote | H15: 23 | L15: =TRUE() -> TRUE | M15: =FALSE() -> FALSE | O15: =TRUE() -> TRUE | P15: 003 | R15: Ok | T15: 0
A16: polpa-de-umbu-brasfrut-pacote-com-12-100-g | B16: Polpa de Umbu | C16: polpas | D16: Polpa 100 g | E16: Brasfrut | F16: Pacote com 12 × 100 g | G16: pacote | H16: 45 | L16: =TRUE() -> TRUE | M16: =FALSE() -> FALSE | O16: =TRUE() -> TRUE | P16: 50017 | Q16: 7896014400911 | R16: Ok | T16: 2
A17: polpa-de-abacaxi-brasfrut-pacote-1-02-kg-vendido-por-kg | B17: Polpa de Abacaxi | C17: polpas | D17: Polpa 1,02 kg | E17: Brasfrut | F17: Pacote 1,02 kg (vendido por kg) | G17: kg | H17: 12 | L17: =TRUE() -> TRUE | M17: =FALSE() -> FALSE | O17: =TRUE() -> TRUE | P17: 80001 | Q17: 7896014400652 | R17: Ok | T17: 250
A18: polpa-de-acerola-brasfrut-pacote-1-02-kg-vendido-por-kg | B18: Polpa de Acerola | C18: polpas | D18: Polpa 1,02 kg | E18: Brasfrut | F18: Pacote 1,02 kg (vendido por kg) | G18: kg | H18: 12 | L18: =TRUE() -> TRUE | M18: =FALSE() -> FALSE | O18: =TRUE() -> TRUE | P18: 80003 | Q18: 7896014400676 | R18: Ok | T18: 318
A19: polpa-de-caju-brasfrut-pacote-1-02-kg-vendido-por-kg | B19: Polpa de Caju | C19: polpas | D19: Polpa 1,02 kg | E19: Brasfrut | F19: Pacote 1,02 kg (vendido por kg) | G19: kg | H19: 12 | L19: =TRUE() -> TRUE | M19: =FALSE() -> FALSE | O19: =TRUE() -> TRUE | P19: 80006 | Q19: 7896014400706 | R19: Ok | T19: 287
A20: polpa-de-goiaba-brasfrut-pacote-1-02-kg-vendido-por-kg | B20: Polpa de Goiaba | C20: polpas | D20: Polpa 1,02 kg | E20: Brasfrut | F20: Pacote 1,02 kg (vendido por kg) | G20: kg | H20: 12 | L20: =TRUE() -> TRUE | M20: =FALSE() -> FALSE | O20: =TRUE() -> TRUE | P20: 80008 | Q20: 7896014400720 | R20: Ok | T20: 229
A21: polpa-de-tamarindo-brasfrut-pacote-1-02-kg-vendido-por-kg | B21: Polpa de Tamarindo | C21: polpas | D21: Polpa 1,02 kg | E21: Brasfrut | F21: Pacote 1,02 kg (vendido por kg) | G21: kg | H21: 12 | L21: =TRUE() -> TRUE | M21: =FALSE() -> FALSE | O21: =TRUE() -> TRUE | P21: 80019 | Q21: 7896014400843 | R21: Ok | T21: 339
A22: file-de-mapara-por-kg | B22: Filé de Mapará | C22: peixes | D22: Peixes e frutos do mar | F22: Por kg | G22: kg | H22: 39.9 | L22: =TRUE() -> TRUE | M22: =FALSE() -> FALSE | O22: =TRUE() -> TRUE | P22: 60 | R22: Ok | T22: 0
A23: polpa-de-maracuja-fauzi-pacote-com-10-100-g | B23: Polpa de Maracujá | C23: polpas | D23: Polpa 100 g | E23: Fauzi | F23: Pacote com 10 × 100 g | G23: pacote | H23: 40 | L23: =TRUE() -> TRUE | M23: =FALSE() -> FALSE | O23: =TRUE() -> TRUE | P23: 00200 | R23: Ok | T23: 0
A24: posta-de-piramutaba-por-kg | B24: Posta de Piramutaba | C24: peixes | D24: Peixes e frutos do mar | F24: Por kg | G24: kg | H24: 19 | L24: =TRUE() -> TRUE | M24: =FALSE() -> FALSE | O24: =TRUE() -> TRUE | P24: 035 | R24: Ok | T24: 0
A25: file-de-merluza-por-kg | B25: Filé de Merluza | C25: peixes | D25: Peixes e frutos do mar | F25: Por kg | G25: kg | H25: 34.6 | L25: =TRUE() -> TRUE | M25: =FALSE() -> FALSE | O25: =TRUE() -> TRUE | P25: 33 | R25: Ok | T25: 0
A26: camarao-cinza-eviscerado-sem-colinha-por-kg | B26: Camarão Cinza Eviscerado sem Colinha | C26: peixes | D26: Peixes e frutos do mar | F26: Por kg | G26: kg | H26: 79.9 | L26: =TRUE() -> TRUE | M26: =FALSE() -> FALSE | O26: =TRUE() -> TRUE | P26: 0400 | R26: Ok | T26: 0
A27: posta-de-pintado-por-kg-pacote-500-g | B27: Posta de Pintado | C27: peixes | D27: Peixes e frutos do mar | F27: Por kg (pacote 500 g) | G27: kg | H27: 26.8 | L27: =TRUE() -> TRUE | M27: =FALSE() -> FALSE | O27: =TRUE() -> TRUE | P27: 0000034 | R27: Conferir | S27: Sistema: 'POSTA DE PINTADO 500G' com unidade KG. Conferir se o preço é por kg ou por pacote. | T27: 0
A28: bolinho-de-bacalhau-pacote-500-g | B28: Bolinho de Bacalhau | C28: salgados | D28: Salgados | F28: Pacote 500 g | G28: pacote | H28: 20 | L28: =TRUE() -> TRUE | M28: =FALSE() -> FALSE | O28: =TRUE() -> TRUE | P28: 50039 | R28: Ok | T28: 0
A29: polpa-de-tangerina-brasfrut-pacote-com-12-100-g | B29: Polpa de Tangerina | C29: polpas | D29: Polpa 100 g | E29: Brasfrut | F29: Pacote com 12 × 100 g | G29: pacote | H29: 60 | L29: =TRUE() -> TRUE | M29: =FALSE() -> FALSE | O29: =TRUE() -> TRUE | P29: 50021 | Q29: 7896014401567 | R29: Ok | T29: 37
A30: bacalhau-desfiado-por-kg | B30: Bacalhau Desfiado | C30: peixes | D30: Peixes e frutos do mar | F30: Por kg | G30: kg | H30: 65 | L30: =TRUE() -> TRUE | M30: =FALSE() -> FALSE | O30: =TRUE() -> TRUE | P30: 151 | R30: Ok | T30: 0.4
A31: casquinha-de-siri-fast-fish-pacote-300-g | B31: Casquinha de Siri | C31: salgados | D31: Salgados | E31: Fast Fish | F31: Pacote 300 g | G31: pacote | H31: 28 | L31: =TRUE() -> TRUE | M31: =FALSE() -> FALSE | O31: =TRUE() -> TRUE | P31: 51318 | R31: Ok | T31: 0
A32: camarao-sete-barbas-por-kg | B32: Camarão Sete Barbas | C32: peixes | D32: Peixes e frutos do mar | F32: Por kg | G32: kg | H32: 54.9 | L32: =TRUE() -> TRUE | M32: =FALSE() -> FALSE | O32: =TRUE() -> TRUE | P32: 10116 | R32: Ok | T32: 0
A33: file-de-tilapia-por-kg | B33: Filé de Tilápia | C33: peixes | D33: Peixes e frutos do mar | F33: Por kg | G33: kg | H33: 49.9 | L33: =TRUE() -> TRUE | M33: =FALSE() -> FALSE | O33: =TRUE() -> TRUE | P33: 20017 | R33: Ok | T33: 0
A34: file-de-pintado-por-kg-pacote-500-g | B34: Filé de Pintado | C34: peixes | D34: Peixes e frutos do mar | F34: Por kg (pacote 500 g) | G34: kg | H34: 27.3 | L34: =TRUE() -> TRUE | M34: =FALSE() -> FALSE | O34: =TRUE() -> TRUE | P34: 527 | R34: Ok | T34: 0
A35: file-de-salmao-premium-por-kg | B35: Filé de Salmão Premium | C35: peixes | D35: Peixes e frutos do mar | F35: Por kg | G35: kg | H35: 96.9 | L35: =TRUE() -> TRUE | M35: =FALSE() -> FALSE | O35: =TRUE() -> TRUE | P35: 530 | R35: Ok | T35: 0
A36: kani-kama-pacote-250-g | B36: Kani Kama | C36: peixes | D36: Peixes e frutos do mar | F36: Pacote 250 g | G36: pacote | H36: 24 | L36: =TRUE() -> TRUE | M36: =FALSE() -> FALSE | O36: =TRUE() -> TRUE | P36: 250 | R36: Ok | T36: 0
A37: file-de-aruana-por-kg | B37: Filé de Aruanã | C37: peixes | D37: Peixes e frutos do mar | F37: Por kg | G37: kg | H37: 23 | L37: =TRUE() -> TRUE | M37: =FALSE() -> FALSE | O37: =TRUE() -> TRUE | P37: 87 | R37: Ok | T37: 0
A38: camarao-rosa-por-kg | B38: Camarão Rosa | C38: peixes | D38: Peixes e frutos do mar | F38: Por kg | G38: kg | H38: 139.9 | L38: =TRUE() -> TRUE | M38: =FALSE() -> FALSE | O38: =TRUE() -> TRUE | P38: 89 | R38: Ok | T38: 0
A39: file-de-robalo-por-kg | B39: Filé de Robalo | C39: peixes | D39: Peixes e frutos do mar | F39: Por kg | G39: kg | H39: 98 | L39: =TRUE() -> TRUE | M39: =FALSE() -> FALSE | O39: =TRUE() -> TRUE | P39: 25 | R39: Ok | T39: 0
A40: posta-de-pintado-por-kg-pacote-700-g | B40: Posta de Pintado | C40: peixes | D40: Peixes e frutos do mar | F40: Por kg (pacote 700 g) | G40: kg | H40: 54 | L40: =TRUE() -> TRUE | M40: =FALSE() -> FALSE | O40: =TRUE() -> TRUE | P40: 526 | R40: Conferir | S40: Sistema: 'PCT 700G' com unidade KG. Conferir se o preço é por kg ou por pacote. | T40: 0
A41: mexilhao-por-kg | B41: Mexilhão | C41: peixes | D41: Peixes e frutos do mar | F41: Por kg | G41: kg | H41: 38 | L41: =TRUE() -> TRUE | M41: =FALSE() -> FALSE | O41: =TRUE() -> TRUE | P41: 777777 | R41: Ok | T41: 0
A42: posta-de-dourada-por-kg | B42: Posta de Dourada | C42: peixes | D42: Peixes e frutos do mar | F42: Por kg | G42: kg | H42: 46.9 | L42: =TRUE() -> TRUE | M42: =FALSE() -> FALSE | O42: =TRUE() -> TRUE | P42: 152 | R42: Ok | T42: 0
A43: camarao-rosa-inteiro-por-kg | B43: Camarão Rosa Inteiro | C43: peixes | D43: Peixes e frutos do mar | F43: Por kg | G43: kg | H43: 88.9 | L43: =TRUE() -> TRUE | M43: =FALSE() -> FALSE | O43: =TRUE() -> TRUE | P43: 292 | R43: Ok | T43: 0
A44: polpa-de-coco-brasfrut-pacote-com-12-100-g | B44: Polpa de Coco | C44: polpas | D44: Polpa 100 g | E44: Brasfrut | F44: Pacote com 12 × 100 g | G44: pacote | H44: 40 | L44: =TRUE() -> TRUE | M44: =FALSE() -> FALSE | O44: =TRUE() -> TRUE | P44: 50023 | Q44: 7896014400355 | R44: Ok | T44: 0 | U44: 50
A45: bacalhau-lombo-morhua-liberalves-por-kg-1-kg | B45: Bacalhau Lombo Morhua | C45: peixes | D45: Peixes e frutos do mar | E45: Liberalves | F45: Por kg (1 kg) | G45: kg | H45: 80 | L45: =TRUE() -> TRUE | M45: =FALSE() -> FALSE | O45: =TRUE() -> TRUE | P45: 97241 | R45: Ok | T45: 0
A46: polpa-de-uva-nature-pacote-com-12-100-g | B46: Polpa de Uva | C46: polpas | D46: Polpa 100 g | E46: Nature | F46: Pacote com 12 × 100 g | G46: pacote | H46: 25 | L46: =TRUE() -> TRUE | M46: =FALSE() -> FALSE | O46: =TRUE() -> TRUE | P46: 70018 | R46: Ok | T46: 0
A47: abacaxi-congelado-pacote-1-02-kg-vendido-por-kg | B47: Abacaxi Congelado | C47: frutas | D47: Frutas congeladas | F47: Pacote 1,02 kg (vendido por kg) | G47: kg | H47: 25 | L47: =TRUE() -> TRUE | M47: =FALSE() -> FALSE | O47: =TRUE() -> TRUE | P47: 70010 | R47: Ok | T47: 0
A48: frutas-vermelhas-congeladas-pacote-1-kg-vendido-por-kg | B48: Frutas Vermelhas Congeladas | C48: frutas | D48: Frutas congeladas | F48: Pacote 1 kg (vendido por kg) | G48: kg | H48: 48 | L48: =TRUE() -> TRUE | M48: =FALSE() -> FALSE | O48: =TRUE() -> TRUE | P48: 70012 | R48: Ok | T48: 2
A49: bolinho-de-bacalhau-caixa-12-360-g-vendido-por-kg | B49: Bolinho de Bacalhau | C49: salgados | D49: Salgados | F49: Caixa 12 × 360 g (vendido por kg) | G49: kg | H49: 71.61 | L49: =TRUE() -> TRUE | M49: =FALSE() -> FALSE | O49: =TRUE() -> TRUE | P49: 204 | R49: Ok | T49: 0
A50: file-de-pirarucu-por-kg | B50: Filé de Pirarucu | C50: peixes | D50: Peixes e frutos do mar | F50: Por kg | G50: kg | H50: 42 | L50: =TRUE() -> TRUE | M50: =FALSE() -> FALSE | O50: =TRUE() -> TRUE | P50: 000400 | R50: Ok | T50: 0
A51: tentaculos-de-polvo-pacote-300-g | B51: Tentáculos de Polvo | C51: peixes | D51: Peixes e frutos do mar | F51: Pacote 300 g | G51: pacote | H51: 36 | L51: =TRUE() -> TRUE | M51: =FALSE() -> FALSE | O51: =TRUE() -> TRUE | P51: 000236 | R51: Ok | T51: 0
A52: bacalhau-lombo-por-kg | B52: Bacalhau Lombo | C52: peixes | D52: Peixes e frutos do mar | F52: Por kg | G52: kg | H52: 187.9 | L52: =TRUE() -> TRUE | M52: =FALSE() -> FALSE | O52: =TRUE() -> TRUE | P52: 000151 | R52: Ok | T52: 0
A53: caranha-inteira-escamada-por-kg | B53: Caranha Inteira Escamada | C53: peixes | D53: Peixes e frutos do mar | F53: Por kg | G53: kg | H53: 39.9 | L53: =TRUE() -> TRUE | M53: =FALSE() -> FALSE | O53: =TRUE() -> TRUE | P53: 000015 | R53: Ok | T53: 0
A54: costelinha-de-caranha-por-kg | B54: Costelinha de Caranha | C54: peixes | D54: Peixes e frutos do mar | F54: Por kg | G54: kg | H54: 39.9 | L54: =TRUE() -> TRUE | M54: =FALSE() -> FALSE | O54: =TRUE() -> TRUE | P54: 000013 | R54: Ok | T54: 0
A55: camarao-sete-barbas-por-kg-pacote-500-g | B55: Camarão Sete Barbas | C55: peixes | D55: Peixes e frutos do mar | F55: Por kg (pacote 500 g) | G55: kg | H55: 35 | L55: =TRUE() -> TRUE | M55: =FALSE() -> FALSE | O55: =TRUE() -> TRUE | P55: 100003 | R55: Ok | T55: 0
A56: camarao-rosa-31-40-por-kg | B56: Camarão Rosa 31/40 | C56: peixes | D56: Peixes e frutos do mar | F56: Por kg | G56: kg | H56: 139.9 | L56: =TRUE() -> TRUE | M56: =FALSE() -> FALSE | O56: =TRUE() -> TRUE | P56: 100101 | R56: Ok | T56: 0
A57: posta-de-mapara-por-kg-pacote-700-g | B57: Posta de Mapará | C57: peixes | D57: Peixes e frutos do mar | F57: Por kg (pacote 700 g) | G57: kg | H57: 16 | L57: =TRUE() -> TRUE | M57: =FALSE() -> FALSE | O57: =TRUE() -> TRUE | P57: 000100 | R57: Conferir | S57: Sistema: R$ 16,00/kg parece baixo. Conferir. | T57: 0
A58: polpa-mista-de-abacaxi-e-hortela-brasfrut-pacote-com-12-100-g | B58: Polpa Mista de Abacaxi e Hortelã | C58: polpas | D58: Polpa 100 g | E58: Brasfrut | F58: Pacote com 12 × 100 g | G58: pacote | H58: 30 | L58: =TRUE() -> TRUE | M58: =FALSE() -> FALSE | O58: =TRUE() -> TRUE | P58: 50025 | Q58: 7896014400331 | R58: Ok | T58: 98 | U58: 38
A59: polpa-de-manga-brasfrut-pacote-1-02-kg-vendido-por-kg | B59: Polpa de Manga | C59: polpas | D59: Polpa 1,02 kg | E59: Brasfrut | F59: Pacote 1,02 kg (vendido por kg) | G59: kg | H59: 12 | L59: =TRUE() -> TRUE | M59: =FALSE() -> FALSE | O59: =TRUE() -> TRUE | P59: 80012 | Q59: 7896014400775 | R59: Ok | T59: 254
A60: polpa-de-amora-brasfrut-pacote-com-12-100-g | B60: Polpa de Amora | C60: polpas | D60: Polpa 100 g | E60: Brasfrut | F60: Pacote com 12 × 100 g | G60: pacote | H60: 60 | L60: =TRUE() -> TRUE | M60: =FALSE() -> FALSE | O60: =TRUE() -> TRUE | P60: 50026 | Q60: 7896014400928 | R60: Ok | T60: 101 | U60: 70
A61: file-de-surubim-pacote-800-g | B61: Filé de Surubim | C61: peixes | D61: Peixes e frutos do mar | F61: Pacote 800 g | G61: pacote | H61: 20 | L61: =TRUE() -> TRUE | M61: =FALSE() -> FALSE | O61: =TRUE() -> TRUE | P61: 002224 | R61: Ok | T61: 0
A62: file-de-cambucu-pacote-800-g | B62: Filé de Cambuçu | C62: peixes | D62: Peixes e frutos do mar | F62: Pacote 800 g | G62: pacote | H62: 44.9 | L62: =TRUE() -> TRUE | M62: =FALSE() -> FALSE | O62: =TRUE() -> TRUE | P62: 12801 | R62: Ok | T62: 0
A63: mirtilo-congelado-por-kg | B63: Mirtilo Congelado | C63: frutas | D63: Frutas congeladas | F63: Por kg | G63: kg | H63: 50 | L63: =TRUE() -> TRUE | M63: =FALSE() -> FALSE | O63: =TRUE() -> TRUE | P63: 7113 | R63: Ok | T63: 0
A64: bolinho-de-camarao-pacote-500-g | B64: Bolinho de Camarão | C64: salgados | D64: Salgados | F64: Pacote 500 g | G64: pacote | H64: 28 | L64: =TRUE() -> TRUE | M64: =FALSE() -> FALSE | O64: =TRUE() -> TRUE | P64: 142123 | R64: Ok | T64: 0
A65: bolinho-de-mandioca-com-carne-seca-pacote-500-g | B65: Bolinho de Mandioca com Carne Seca | C65: salgados | D65: Salgados | F65: Pacote 500 g | G65: pacote | H65: 28 | L65: =TRUE() -> TRUE | M65: =FALSE() -> FALSE | O65: =TRUE() -> TRUE | P65: 141242 | R65: Ok | T65: 0
A66: kibe-de-tilapia-com-queijo-pacote-500-g | B66: Kibe de Tilápia com Queijo | C66: salgados | D66: Salgados | F66: Pacote 500 g | G66: un | H66: 26 | L66: =TRUE() -> TRUE | M66: =FALSE() -> FALSE | O66: =TRUE() -> TRUE | P66: 349 | R66: Ok | T66: 0
A67: bolinho-de-tucunare-com-queijo-pacote-500-g | B67: Bolinho de Tucunaré com Queijo | C67: salgados | D67: Salgados | F67: Pacote 500 g | G67: pacote | H67: 28 | L67: =TRUE() -> TRUE | M67: =FALSE() -> FALSE | O67: =TRUE() -> TRUE | P67: 14124 | R67: Ok | T67: 0
A68: torresmo-recheado-pacote-500-g | B68: Torresmo Recheado | C68: salgados | D68: Salgados | F68: Pacote 500 g | G68: pacote | H68: 28 | L68: =TRUE() -> TRUE | M68: =FALSE() -> FALSE | O68: =TRUE() -> TRUE | P68: 142125 | R68: Ok | T68: 0
A69: mini-pastel-de-carne-la-fig-pacote-280-g | B69: Mini Pastel de Carne | C69: salgados | D69: Salgados | E69: La Fig | F69: Pacote 280 g | G69: pacote | H69: 25 | L69: =TRUE() -> TRUE | M69: =FALSE() -> FALSE | O69: =TRUE() -> TRUE | P69: 1421243 | R69: Ok | T69: 0
A70: mini-pastel-de-queijo-la-fig-pacote-280-g | B70: Mini Pastel de Queijo | C70: salgados | D70: Salgados | E70: La Fig | F70: Pacote 280 g | G70: pacote | H70: 25 | L70: =TRUE() -> TRUE | M70: =FALSE() -> FALSE | O70: =TRUE() -> TRUE | P70: 1421244 | R70: Ok | T70: 0
A71: bolinho-de-cabotia-com-carne-seca-pacote-500-g | B71: Bolinho de Cabotiá com Carne Seca | C71: salgados | D71: Salgados | F71: Pacote 500 g | G71: pacote | H71: 28 | L71: =TRUE() -> TRUE | M71: =FALSE() -> FALSE | O71: =TRUE() -> TRUE | P71: 2525 | R71: Ok | T71: 0
A72: morango-congelado-frut-center-pacote-1-02-kg-vendido-por-kg | B72: Morango Congelado | C72: frutas | D72: Frutas congeladas | E72: Frut Center | F72: Pacote 1,02 kg (vendido por kg) | G72: kg | H72: 19 | L72: =TRUE() -> TRUE | M72: =FALSE() -> FALSE | O72: =TRUE() -> TRUE | P72: 809 | R72: Ok | T72: 69
A73: lombo-de-pintado-por-kg | B73: Lombo de Pintado | C73: peixes | D73: Peixes e frutos do mar | F73: Por kg | G73: kg | H73: 86 | L73: =TRUE() -> TRUE | M73: =FALSE() -> FALSE | O73: =TRUE() -> TRUE | P73: 238 | R73: Ok | T73: 0
A74: manjuba-inteira-pacote-800-g | B74: Manjuba Inteira | C74: peixes | D74: Peixes e frutos do mar | F74: Pacote 800 g | G74: pacote | H74: 22 | L74: =TRUE() -> TRUE | M74: =FALSE() -> FALSE | O74: =TRUE() -> TRUE | P74: 80622 | R74: Ok | T74: 0
A75: morango-congelado-pacote-1-02-kg-vendido-por-kg | B75: Morango Congelado | C75: frutas | D75: Frutas congeladas | F75: Pacote 1,02 kg (vendido por kg) | G75: kg | H75: 19 | L75: =TRUE() -> TRUE | M75: =FALSE() -> FALSE | O75: =TRUE() -> TRUE | P75: 0611 | R75: Conferir | S75: Sistema: marca FrutBras (maior estoque). No site sem marca e sem foto da embalagem. Confirmar com o chefe. | T75: 759 | U75: 22
A76: file-de-panga-pacote-400-g | B76: Filé de Panga | C76: peixes | D76: Peixes e frutos do mar | F76: Pacote 400 g | G76: pacote | H76: 20 | L76: =TRUE() -> TRUE | M76: =FALSE() -> FALSE | O76: =TRUE() -> TRUE | P76: 999929 | R76: Ok | T76: 0
A77: sardinha-laje-pacote-400-g | B77: Sardinha Laje | C77: peixes | D77: Peixes e frutos do mar | F77: Pacote 400 g | G77: pacote | H77: 12.78 | L77: =TRUE() -> TRUE | M77: =FALSE() -> FALSE | O77: =TRUE() -> TRUE | P77: 999930 | R77: Ok | T77: 0
A78: sardinha-laje-eviscerada-por-kg | B78: Sardinha Laje Eviscerada | C78: peixes | D78: Peixes e frutos do mar | F78: Por kg | G78: kg | H78: 15.43 | L78: =TRUE() -> TRUE | M78: =FALSE() -> FALSE | O78: =TRUE() -> TRUE | P78: 999931 | R78: Ok | T78: 0
A79: amora-congelada-por-kg | B79: Amora Congelada | C79: frutas | D79: Frutas congeladas | F79: Por kg | G79: kg | H79: 25 | L79: =TRUE() -> TRUE | M79: =FALSE() -> FALSE | O79: =TRUE() -> TRUE | P79: 253 | R79: Ok | T79: 0
A80: framboesa-congelada-por-kg | B80: Framboesa Congelada | C80: frutas | D80: Frutas congeladas | F80: Por kg | G80: kg | H80: 68 | L80: =TRUE() -> TRUE | M80: =FALSE() -> FALSE | O80: =TRUE() -> TRUE | P80: 252 | R80: Ok | T80: 0
A81: framboesa-congelada-peterfrut-bandeja-500-g | B81: Framboesa Congelada | C81: frutas | D81: Frutas congeladas | E81: Peterfrut | F81: Bandeja 500 g | G81: bandeja | H81: 27.6 | L81: =TRUE() -> TRUE | M81: =FALSE() -> FALSE | O81: =TRUE() -> TRUE | P81: 000092 | R81: Ok | T81: 0
A82: morango-congelado-ahs-pacote-1-02-kg-vendido-por-kg | B82: Morango Congelado | C82: frutas | D82: Frutas congeladas | E82: AHS | F82: Pacote 1,02 kg (vendido por kg) | G82: kg | H82: 19 | L82: =TRUE() -> TRUE | M82: =FALSE() -> FALSE | O82: =TRUE() -> TRUE | P82: 000254 | R82: Ok | T82: 0
A83: bolinho-de-tilapia-com-queijo-pacote-500-g | B83: Bolinho de Tilápia com Queijo | C83: salgados | D83: Salgados | F83: Pacote 500 g | G83: pacote | H83: 30 | L83: =TRUE() -> TRUE | M83: =FALSE() -> FALSE | O83: =TRUE() -> TRUE | P83: 545 | R83: Ok | T83: 0
A84: camarao-desc-eviscerado-cauda-41-50-por-kg | B84: Camarão Desc. Eviscerado Cauda 41/50 | C84: peixes | D84: Peixes e frutos do mar | F84: Por kg | G84: kg | H84: 54 | L84: =TRUE() -> TRUE | M84: =FALSE() -> FALSE | O84: =TRUE() -> TRUE | P84: 10000005 | R84: Ok | T84: 0
A85: camarao-cinza-41-50-por-kg | B85: Camarão Cinza 41/50 | C85: peixes | D85: Peixes e frutos do mar | F85: Por kg | G85: kg | H85: 98.9 | L85: =TRUE() -> TRUE | M85: =FALSE() -> FALSE | O85: =TRUE() -> TRUE | P85: 000948 | R85: Ok | T85: 0
A86: camarao-cinza-empanado-sem-cauda-bandeja-350-g | B86: Camarão Cinza Empanado sem Cauda | C86: peixes | D86: Peixes e frutos do mar | F86: Bandeja 350 g | G86: pacote | H86: 89.9 | L86: =TRUE() -> TRUE | M86: =FALSE() -> FALSE | O86: =TRUE() -> TRUE | P86: 000914 | R86: Ok | T86: 0
A87: bolinho-de-costela-pacote-500-g | B87: Bolinho de Costela | C87: salgados | D87: Salgados | F87: Pacote 500 g | G87: pacote | H87: 27 | L87: =TRUE() -> TRUE | M87: =FALSE() -> FALSE | O87: =TRUE() -> TRUE | P87: 12345 | R87: Ok | T87: 0
A88: gelo-saborizado-agua-de-coco-coco-leve-190-g | B88: Gelo Saborizado Água de Coco | C88: gelo | D88: Coco Leve | E88: Coco Leve | F88: 190 g | G88: un | H88: 2.6 | L88: =TRUE() -> TRUE | M88: =FALSE() -> FALSE | O88: =TRUE() -> TRUE | P88: 515 | R88: Conferir | S88: Sistema: unidade 'CX' mas preço de R$ 2,60 parece ser por unidade. Catálogo do fornecedor diz 55 g; sistema diz 190 g. Conferir. | T88: 63 | U88: 3.5
A89: gelo-saborizado-laranja-coco-leve-190-g | B89: Gelo Saborizado Laranja | C89: gelo | D89: Coco Leve | E89: Coco Leve | F89: 190 g | G89: un | H89: 2.6 | L89: =TRUE() -> TRUE | M89: =FALSE() -> FALSE | O89: =TRUE() -> TRUE | P89: 516 | R89: Conferir | S89: Sistema: unidade 'CX' mas preço de R$ 2,60 parece ser por unidade. Catálogo do fornecedor diz 55 g; sistema diz 190 g. Conferir. | T89: 2 | U89: 3.5
A90: gelo-saborizado-limao-coco-leve-190-g | B90: Gelo Saborizado Limão | C90: gelo | D90: Coco Leve | E90: Coco Leve | F90: 190 g | G90: un | H90: 2.6 | L90: =TRUE() -> TRUE | M90: =FALSE() -> FALSE | O90: =TRUE() -> TRUE | P90: 517 | R90: Conferir | S90: Sistema: unidade 'CX' mas preço de R$ 2,60 parece ser por unidade. Catálogo do fornecedor diz 55 g; sistema diz 190 g. Conferir. | T90: 3 | U90: 3.5
A91: gelo-saborizado-maca-verde-coco-leve-190-g | B91: Gelo Saborizado Maçã Verde | C91: gelo | D91: Coco Leve | E91: Coco Leve | F91: 190 g | G91: un | H91: 2.6 | L91: =TRUE() -> TRUE | M91: =FALSE() -> FALSE | O91: =TRUE() -> TRUE | P91: 518 | R91: Conferir | S91: Sistema: unidade 'CX' mas preço de R$ 2,60 parece ser por unidade. Catálogo do fornecedor diz 55 g; sistema diz 190 g. Conferir. | T91: 72 | U91: 3.5
A92: gelo-saborizado-maracuja-coco-leve-190-g | B92: Gelo Saborizado Maracujá | C92: gelo | D92: Coco Leve | E92: Coco Leve | F92: 190 g | G92: un | H92: 2.6 | L92: =TRUE() -> TRUE | M92: =FALSE() -> FALSE | O92: =TRUE() -> TRUE | P92: 519 | R92: Conferir | S92: Sistema: unidade 'CX' mas preço de R$ 2,60 parece ser por unidade. Catálogo do fornecedor diz 55 g; sistema diz 190 g. Conferir. | T92: 208 | U92: 3.5
A93: gelo-saborizado-melancia-coco-leve-190-g | B93: Gelo Saborizado Melancia | C93: gelo | D93: Coco Leve | E93: Coco Leve | F93: 190 g | G93: un | H93: 2.6 | L93: =TRUE() -> TRUE | M93: =FALSE() -> FALSE | O93: =TRUE() -> TRUE | P93: 520 | R93: Conferir | S93: Sistema: unidade 'CX' mas preço de R$ 2,60 parece ser por unidade. Catálogo do fornecedor diz 55 g; sistema diz 190 g. Conferir. | T93: 75 | U93: 3.5
A94: gelo-saborizado-morango-coco-leve-190-g | B94: Gelo Saborizado Morango | C94: gelo | D94: Coco Leve | E94: Coco Leve | F94: 190 g | G94: un | H94: 2.6 | L94: =TRUE() -> TRUE | M94: =FALSE() -> FALSE | O94: =TRUE() -> TRUE | P94: 522 | R94: Conferir | S94: Sistema: unidade 'CX' mas preço de R$ 2,60 parece ser por unidade. Catálogo do fornecedor diz 55 g; sistema diz 190 g. Conferir. | T94: 70 | U94: 3.5
A95: gelo-saborizado-sal-e-limao-cerveja-coco-leve-190-g | B95: Gelo Saborizado Sal e Limão (cerveja) | C95: gelo | D95: Coco Leve | E95: Coco Leve | F95: 190 g | G95: un | H95: 2.6 | L95: =TRUE() -> TRUE | M95: =FALSE() -> FALSE | O95: =TRUE() -> TRUE | P95: 524 | R95: Conferir | S95: Sistema: unidade 'CX' mas preço de R$ 2,60 parece ser por unidade. Catálogo do fornecedor diz 55 g; sistema diz 190 g. Conferir. | T95: 97 | U95: 3.5
A96: camarao-cinza-descascado-61-70-por-kg | B96: Camarão Cinza Descascado 61/70 | C96: peixes | D96: Peixes e frutos do mar | F96: Por kg | G96: kg | H96: 83.86 | L96: =TRUE() -> TRUE | M96: =FALSE() -> FALSE | O96: =TRUE() -> TRUE | P96: 213 | R96: Ok | T96: 0 | U96: 89.85
A97: polpa-de-acai-organico-pasteurizado-brasfrut-pacote-com-4-100-g | B97: Polpa de Açaí Orgânico Pasteurizado | C97: polpas | D97: Polpa 100 g | E97: Brasfrut | F97: Pacote com 4 × 100 g | G97: pacote | H97: 18 | L97: =TRUE() -> TRUE | M97: =FALSE() -> FALSE | O97: =TRUE() -> TRUE | P97: 50014 | Q97: 7896014401239 | R97: Ok | T97: 393 | U97: 19
A98: manjuba-inteira-pacote-400-g | B98: Manjuba Inteira | C98: peixes | D98: Peixes e frutos do mar | F98: Pacote 400 g | G98: pacote | H98: 22 | L98: =TRUE() -> TRUE | M98: =FALSE() -> FALSE | O98: =TRUE() -> TRUE | P98: 80623 | R98: Ok | T98: 0
A99: gelo-saborizado-xeque-mate-limao-e-gengibre-coco-leve-190-g | B99: Gelo Saborizado Xeque Mate (limão e gengibre) | C99: gelo | D99: Coco Leve | E99: Coco Leve | F99: 190 g | G99: un | H99: 2.6 | L99: =TRUE() -> TRUE | M99: =FALSE() -> FALSE | O99: =TRUE() -> TRUE | P99: 739 | R99: Conferir | S99: Sistema: unidade 'CX' mas preço de R$ 2,60 parece ser por unidade. Catálogo do fornecedor diz 55 g; sistema diz 190 g. Conferir. | T99: 6 | U99: 3.5
A100: gelo-saborizado-beats-gt-limao-gengibre-e-hortela-coco-leve-190-g | B100: Gelo Saborizado Beats GT (limão, gengibre e hortelã) | C100: gelo | D100: Coco Leve | E100: Coco Leve | F100: 190 g | G100: un | H100: 2.6 | L100: =TRUE() -> TRUE | M100: =FALSE() -> FALSE | O100: =TRUE() -> TRUE | P100: 721 | R100: Conferir | S100: Sistema: unidade 'CX' mas preço de R$ 2,60 parece ser por unidade. Catálogo do fornecedor diz 55 g; sistema diz 190 g. Conferir. | T100: 9 | U100: 3.5
...

Sheet Catálogo fornecedores
A1: Itens dos catálogos dos fornecedores que NÃO estão na lista do sistema (ou estão com outro nome). Não vão para o site.
A2: Para vender algum deles, copie a linha para a aba Produtos, preencha preço e unidadeVenda e gere o id. Vários peixes daqui podem ser os mesmos do sistema com nome parecido.
A4: nome | B4: categoria | C4: subcategoria | D4: marca | E4: embalagem | F4: ean | G4: código do fornecedor
A5: Polpa de Cacau | B5: polpas | C5: Polpa 1,02 kg | D5: Brasfrut | E5: 1,02 kg | F5: 7896014400683
A6: Polpa de Cajá | B6: polpas | C6: Polpa 1,02 kg | D6: Brasfrut | E6: 1,02 kg | F6: 7896014400690
A7: Polpa de Tangerina | B7: polpas | C7: Polpa 1,02 kg | D7: Brasfrut | E7: 1,02 kg | F7: 7896014400850
A8: Polpa de Umbu | B8: polpas | C8: Polpa 1,02 kg | D8: Brasfrut | E8: 1,02 kg | F8: 7896014400867
A9: Néctar de Abacaxi | B9: polpas | C9: Néctar 200 ml | D9: Brasfrut | E9: 200 ml | F9: 7896014403202
A10: Néctar de Acerola | B10: polpas | C10: Néctar 200 ml | D10: Brasfrut | E10: 200 ml | F10: 7896014403165
A11: Néctar de Caju | B11: polpas | C11: Néctar 200 ml | D11: Brasfrut | E11: 200 ml | F11: 7896014403110
A12: Néctar de Goiaba | B12: polpas | C12: Néctar 200 ml | D12: Brasfrut | E12: 200 ml | F12: 7896014403219
A13: Néctar de Manga | B13: polpas | C13: Néctar 200 ml | D13: Brasfrut | E13: 200 ml | F13: 7896014403127
A14: Néctar de Umbu | B14: polpas | C14: Néctar 200 ml | D14: Brasfrut | E14: 200 ml | F14: 7896014403141
A15: Néctar de Uva | B15: polpas | C15: Néctar 200 ml | D15: Brasfrut | E15: 200 ml | F15: 7896014403226
A16: Néctar de Tangerina | B16: polpas | C16: Néctar 200 ml | D16: Brasfrut | E16: 200 ml | F16: 7896014403189
... A18: Néctar de Misto de Maracujá e Maçã | B18: polpas | C18: Néctar 200 ml | D18: Brasfrut | E18: 200 ml | F18: 7896014403240
A19: Morango Congelado | B19: frutas | C19: Frutas congeladas | D19: Frut Polpas | E19: 1,02 kg
A20: Morango Congelado | B20: frutas | C20: Frutas congeladas | D20: Frut Polpas | E20: 100 g
A21: Amorango Congelado (morango e amora) | B21: frutas | C21: Frutas congeladas | D21: Frut Polpas | E21: 1,02 kg
A22: Frutas Vermelhas Congeladas | B22: frutas | C22: Frutas congeladas | D22: Frut Polpas | E22: 1,02 kg
A23: Amoras Congeladas | B23: frutas | C23: Frutas congeladas | D23: Frut Polpas | E23: 1,02 kg
A24: Polpa de Maracujá com Semente | B24: frutas | C24: Frutas congeladas | D24: Frut Polpas | E24: 1,02 kg
A25: Açaí & Frutas Vermelhas | B25: acai-cremes | C25: Açaí | D25: Frut Polpas | E25: 1,02 L
A26: Açaí Tradicional (com guaraná) | B26: acai-cremes | C26: Açaí | D26: Frut Polpas | E26: 1,02 L
A27: Açaí & Maracujá | B27: acai-cremes | C27: Açaí | D27: Frut Polpas | E27: 1,02 L
A28: Açaí & Leitíssimo Crocante | B28: acai-cremes | C28: Açaí | D28: Frut Polpas | E28: 1,02 L
A29: Açaí Tradicional 5 L | B29: acai-cremes | C29: Açaí | D29: Frut Polpas | E29: 5 L
A30: Creme de Manga | B30: acai-cremes | C30: Cremes Frut Polpas | D30: Frut Polpas | E30: 1,02 kg (1,3 L)
... A48: Gelo Saborizado Amore | B48: gelo | C48: Linha especial | D48: Coco Leve | E48: 55 g
A49: Brownie Bites Chocolate Branco | B49: sobremesas | C49: Sobremesas | D49: Kaffinée | E49: 100 g | G49: 219
A50: Brownie Bites Chocolate ao Leite | B50: sobremesas | C50: Sobremesas | D50: Kaffinée | E50: 100 g | G50: 217
A51: Torta Duo Chocolate | B51: sobremesas | C51: Sobremesas | D51: Kaffinée | E51: 200 g (2 un. de 100 g) | G51: 404
A52: Torta de Chocolate | B52: sobremesas | C52: Sobremesas | D52: Kaffinée | E52: 200 g (2 un. de 100 g) | G52: 406
A53: Bolinho de Bacalhau | B53: salgados | C53: Salgados | E53: Consultar
A54: Bolinho de Camarão | B54: salgados | C54: Salgados | E54: Consultar
A55: Bolinho de Tilápia com Queijo | B55: salgados | C55: Salgados | E55: Consultar
A56: Kibe de Tilápia com Queijo | B56: salgados | C56: Salgados | E56: Consultar
A57: Isca de Tilápia | B57: salgados | C57: Salgados | E57: Consultar
A58: Bolinho de Mandioca com Carne Seca | B58: salgados | C58: Salgados | E58: Consultar
A59: Bolinho de Cabotiá com Carne Seca | B59: salgados | C59: Salgados | E59: Consultar
A60: Bolinho de Costela | B60: salgados | C60: Salgados | E60: Consultar
A61: Bolinho de Frango com Catupiry | B61: salgados | C61: Salgados | E61: Consultar
A62: Casquinha de Siri ou de Tilápia | B62: salgados | C62: Salgados | E62: Consultar
A63: Bolinho de Linguiça com Pimenta Biquinho | B63: salgados | C63: Salgados | E63: Consultar
A64: Pastelzinho de Carne | B64: salgados | C64: Salgados | E64: Consultar
... A72: Mandioca Cremosa Tradicional com Calabresa à Salsa | B72: salgados | C72: Salgados | E72: Consultar
A73: BABAO INTEIRO -3 | B73: peixes | C73: Peixes de couro | D73: CenterFish | E73: Consultar | G73: 230
A74: BABAO POSTAS GRANEL | B74: peixes | C74: Peixes de couro | D74: CenterFish | E74: Consultar | G74: 275
A75: BARBADO INTEIRO COM CABEÇA 700/1000 | B75: peixes | C75: Peixes de couro | D75: CenterFish | E75: Consultar | G75: 6
A76: DOURADA INTEIRA -3 | B76: peixes | C76: Peixes de couro | D76: CenterFish | E76: Consultar | G76: 564
A77: DOURADA POSTAS -3 GRANEL | B77: peixes | C77: Peixes de couro | D77: CenterFish | E77: Consultar | G77: 568
A78: FILHOTE INTEIRO -3 | B78: peixes | C78: Peixes de couro | D78: CenterFish | E78: Consultar | G78: 712
A79: FILHOTE POSTA -3 GRANEL | B79: peixes | C79: Peixes de couro | D79: CenterFish | E79: Consultar | G79: 61
A80: JAU INTEIRO | B80: peixes | C80: Peixes de couro | D80: CenterFish | E80: Consultar | G80: 636
A81: JAU POSTAS GRANEL | B81: peixes | C81: Peixes de couro | D81: CenterFish | E81: Consultar | G81: 412
A82: JUNDIA EVISCERADO C/ CABEÇA | B82: peixes | C82: Peixes de couro | D82: CenterFish | E82: Consultar | G82: 549
A83: JUNDIA POSTAS GRANEL | B83: peixes | C83: Peixes de couro | D83: CenterFish | E83: Consultar | G83: 549
A84: MANDI INTEIRO RESFRIADO | B84: peixes | C84: Peixes de couro | D84: CenterFish | E84: Consultar | G84: 11
... A267: FARINHA TEMPERADA PARA EMPANAR | B267: peixes | C267: Natubras (camarão, lula e outros) | D267: Natubras | E267: Consultar | G267: 785

Sheet Como preencher
A1: Planilha de produtos FrutMar
A2: Base do site. A aba Produtos tem os itens da lista do sistema antigo, com preço. Células com fundo creme são as que você edita; cinza é só referência.
A4: Coluna | B4: O que colocar
A5: id | B5: Já gerado. Minúsculo, sem acento, único. Não mude depois que o site estiver no ar (o carrinho usa o id).
A6: nome | B6: Como o cliente vai ler no site.
A7: categoria | B7: Lista: polpas, frutas, acai-cremes, gelo, sobremesas, salgados, peixes. Néctares e polpas em 'polpas'; camarão e frutos do mar em 'peixes'.
A8: subcategoria | B8: Texto livre para agrupar dentro da categoria.
A9: marca | B9: Marca do fornecedor. Vazio se não tiver.
A10: embalagem | B10: O que o cliente recebe. Ex.: 'Pacote com 12 × 100 g', 'Por kg'.
A11: unidadeVenda | B11: Como o preço é cobrado: un, pacote, kg, caixa ou bandeja. O site mostra 'R$ 30,00 / pacote'.
A12: preco | B12: Preço de venda por unidadeVenda, só o número (12,50). Vazio = 'Consulte o preço'. Veio da coluna 'Preço de Venda' do sistema.
A13: caixaQuantidade / caixaPreco | B13: Opcional: se o produto também vende caixa fechada, quantas unidades e o preço. Vazio = não vende por caixa.
A14: foto | B14: Nome do arquivo em src/assets/produtos/ (ex.: polpa-maracuja.jpg). Vazio = imagem padrão com o símbolo.
A15: disponivel | B15: TRUE = pode pedir. FALSE = mostra 'Em falta'.
... A24: precoRevenda | B24: Preço de revenda do sistema. Só referência, não vai para o site.
A26: Exemplo ilustrativo
A27: nome | B27: Polpa de Maracujá
A28: embalagem | B28: Pacote com 12 × 100 g
A29: unidadeVenda | B29: pacote
A30: preco | B30: 60,00
A31: foto | B31: polpa-maracuja.jpg
A32: publicar | B32: TRUE
B33: Só para mostrar o formato: os preços reais estão na aba Produtos.
A35: Depois de editar
B36: 1) Salve a aba Produtos como CSV UTF-8 com o nome produtos.csv, na raiz do projeto. 2) npm run produtos (valida e gera src/data/produtos.json). 3) Commit e push: o site atualiza sozinho.

Sheet Pendências
A1: Pendências e decisões
A3: 1 | B3: Preço igual para todos? | C3: O sistema tem 'Preço de Venda' e 'Preço de Revenda' (revenda é maior, ex.: polpa R$ 30 x R$ 38). O site usa só o Preço de Venda, porque vocês disseram que o preço é o mesmo para todos. Confirmar com o chefe. O Preço de Revenda ficou na coluna de referência.
A4: 2 | B4: Polpas 100 g: pacote de 12 | C4: No sistema a polpa 100 g é vendida por PACOTE com 12 (ex.: R$ 30,00, ou R$ 2,50 a polpa). O site mostra 'R$ 30,00 / pacote'. Decidir se o consumidor final pode comprar só 1 polpa avulsa, e a que preço. Hoje não existe esse item no sistema.
A5: 3 | B5: Polpas 1,02 kg e frutas: preço por kg | C5: O sistema cobra por KG (ex.: polpa 1,02 kg a R$ 12,00/kg). O site mostra 'R$ 12,00 / kg'. Decidir se o cliente pede em kg ou por pacote inteiro (1,02 kg = R$ 12,24). O pedido pelo site aceita quantidade com meio kg.
A6: 4 | B6: Cremes Brasfrut | C6: Sistema: 'CX 06X1,02KG' a R$ 18,66 a R$ 27,80. O preço parece ser por pote, não por caixa de 6. Conferir. Está marcado 'Conferir'.
A7: 5 | B7: Gelo Coco Leve | C7: Sistema: 190 g, unidade 'CX', R$ 2,60. O catálogo do fornecedor diz 55 g. Conferir peso e se o preço é por unidade.
A8: 6 | B8: Peixes: unidade KG com peso na descrição | C8: Posta de pintado 500 g / 700 g, posta de mapará 700 g e filé de pintado 500 g têm unidade KG. O preço parece por kg, mas alguns valores são baixos (mapará R$ 16,00). Conferir.
A9: 7 | B9: Morango com marca FrutBras | C9: O item 0611 'Morango Fruta FrutBras 1,02 kg' tem o maior estoque do sistema (759). No site aparece só como 'Morango Congelado', sem marca e sem foto da embalagem, junto com Frut Center e AHS. Confirmar com o chefe se mostra os três ou só um.
A10: 8 | B10: Outras marcas de polpa | C10: O sistema tem polpas Nature, Canaã, Nutricau e Fauzi, quase todas com estoque zero. Estão na aba Produtos com publicar = TRUE. Decidir se ficam ou saem do site (publicar = FALSE).
A11: 9 | B11: Estoque | C11: 100 dos 154 itens estão com estoque 0 no sistema (quase todos os peixes e salgados). Pode ser que o estoque desses itens não seja controlado. Decidir a regra do site: mostrar sempre, mostrar 'Em falta' ou esconder (pergunta 7 do PRD). O estoque não entra no site; ele muda todo dia.
A12: 10 | B12: Itens que não são produtos | C12: Ficaram de fora: Frete 8% (1602), Freezer 300 L (20253) e um injetor de veículo (00204).
A13: 11 | B13: Código de barras do sistema | C13: As colunas de EAN do sistema vieram cortadas (10 dígitos, repetidas). Não foram usadas. O EAN completo vem do catálogo Brasfrut.
A14: 12 | B14: Itens do catálogo fora da lista | C14: Brownie Bites, tortas, néctares, cremes de açaí de 3 kg, Açaí Frut Polpas, salgados do catálogo e ~190 peixes do catálogo CenterFish não aparecem (ou aparecem com outro nome) no sistema. Estão na aba 'Catálogo fornecedores' como referência.
... A17: 15 | B17: Categorias | C17: O PRD tem 7 categorias. Néctares (só no catálogo) iriam para 'polpas' e camarão/frutos do mar ficam em 'peixes'.

Sheet Resumo
A1: Resumo por categoria (aba Produtos)
A3: Categoria | B3: Produtos | C3: Com preço | D3: A conferir | E3: Para publicar | F3: Estoque zero
A4: polpas | B4: =COUNTIF(Produtos!$C$2:$C$2000,A4) -> 39 | C4: =COUNTIFS(Produtos!$C$2:$C$2000,A4,Produtos!$H$2:$H$2000,">0") -> 39 | D4: =COUNTIFS(Produtos!$C$2:$C$2000,A4,Produtos!$R$2:$R$2000,"Conferir") -> 1 | E4: =COUNTIFS(Produtos!$C$2:$C$2000,A4,Produtos!$O$2:$O$2000,TRUE()) -> 39 | F4: =COUNTIFS(Produtos!$C$2:$C$2000,A4,Produtos!$T$2:$T$2000,0) -> 10
A5: frutas | B5: =COUNTIF(Produtos!$C$2:$C$2000,A5) -> 9 | C5: =COUNTIFS(Produtos!$C$2:$C$2000,A5,Produtos!$H$2:$H$2000,">0") -> 9 | D5: =COUNTIFS(Produtos!$C$2:$C$2000,A5,Produtos!$R$2:$R$2000,"Conferir") -> 1 | E5: =COUNTIFS(Produtos!$C$2:$C$2000,A5,Produtos!$O$2:$O$2000,TRUE()) -> 9 | F5: =COUNTIFS(Produtos!$C$2:$C$2000,A5,Produtos!$T$2:$T$2000,0) -> 6
A6: acai-cremes | B6: =COUNTIF(Produtos!$C$2:$C$2000,A6) -> 6 | C6: =COUNTIFS(Produtos!$C$2:$C$2000,A6,Produtos!$H$2:$H$2000,">0") -> 6 | D6: =COUNTIFS(Produtos!$C$2:$C$2000,A6,Produtos!$R$2:$R$2000,"Conferir") -> 6 | E6: =COUNTIFS(Produtos!$C$2:$C$2000,A6,Produtos!$O$2:$O$2000,TRUE()) -> 6 | F6: =COUNTIFS(Produtos!$C$2:$C$2000,A6,Produtos!$T$2:$T$2000,0) -> 4
A7: gelo | B7: =COUNTIF(Produtos!$C$2:$C$2000,A7) -> 18 | C7: =COUNTIFS(Produtos!$C$2:$C$2000,A7,Produtos!$H$2:$H$2000,">0") -> 18 | D7: =COUNTIFS(Produtos!$C$2:$C$2000,A7,Produtos!$R$2:$R$2000,"Conferir") -> 18 | E7: =COUNTIFS(Produtos!$C$2:$C$2000,A7,Produtos!$O$2:$O$2000,TRUE()) -> 18 | F7: =COUNTIFS(Produtos!$C$2:$C$2000,A7,Produtos!$T$2:$T$2000,0) -> 1
A8: sobremesas | B8: =COUNTIF(Produtos!$C$2:$C$2000,A8) -> 12 | C8: =COUNTIFS(Produtos!$C$2:$C$2000,A8,Produtos!$H$2:$H$2000,">0") -> 12 | D8: =COUNTIFS(Produtos!$C$2:$C$2000,A8,Produtos!$R$2:$R$2000,"Conferir") -> 0 | E8: =COUNTIFS(Produtos!$C$2:$C$2000,A8,Produtos!$O$2:$O$2000,TRUE()) -> 12 | F8: =COUNTIFS(Produtos!$C$2:$C$2000,A8,Produtos!$T$2:$T$2000,0) -> 10
A9: salgados | B9: =COUNTIF(Produtos!$C$2:$C$2000,A9) -> 22 | C9: =COUNTIFS(Produtos!$C$2:$C$2000,A9,Produtos!$H$2:$H$2000,">0") -> 22 | D9: =COUNTIFS(Produtos!$C$2:$C$2000,A9,Produtos!$R$2:$R$2000,"Conferir") -> 0 | E9: =COUNTIFS(Produtos!$C$2:$C$2000,A9,Produtos!$O$2:$O$2000,TRUE()) -> 22 | F9: =COUNTIFS(Produtos!$C$2:$C$2000,A9,Produtos!$T$2:$T$2000,0) -> 22
A10: peixes | B10: =COUNTIF(Produtos!$C$2:$C$2000,A10) -> 48 | C10: =COUNTIFS(Produtos!$C$2:$C$2000,A10,Produtos!$H$2:$H$2000,">0") -> 48 | D10: =COUNTIFS(Produtos!$C$2:$C$2000,A10,Produtos!$R$2:$R$2000,"Conferir") -> 3 | E10: =COUNTIFS(Produtos!$C$2:$C$2000,A10,Produtos!$O$2:$O$2000,TRUE()) -> 48 | F10: =COUNTIFS(Produtos!$C$2:$C$2000,A10,Produtos!$T$2:$T$2000,0) -> 47
A11: Total | B11: =SUM(B4:B10) -> 154 | C11: =SUM(C4:C10) -> 154 | D11: =SUM(D4:D10) -> 29 | E11: =SUM(E4:E10) -> 154 | F11: =SUM(F4:F10) -> 100
